README.txt
setup.py
back_test/__init__.py
back_test/backtest.py
return_portfolio.egg-info/PKG-INFO
return_portfolio.egg-info/SOURCES.txt
return_portfolio.egg-info/dependency_links.txt
return_portfolio.egg-info/requires.txt
return_portfolio.egg-info/top_level.txt