Metadata-Version: 1.1
Name: return-portfolio
Version: 0.0.1
Summary: Calculate portfolio returns
Home-page: UNKNOWN
Author: Shawn Jiang
Author-email: shawnjiang619@gmail.com
License: MIT
Keywords: return portfolio
Platform: UNKNOWN
Classifier: Development Status :: 5 - Production/Stable
Classifier: Intended Audience :: Education
Classifier: License :: OSI Approved :: MIT License
Classifier: Programming Language :: Python :: 3
